<?xml version="1.0" encoding="utf-8"?>
<SelfCheckSetting>
  <ASM>
    <boolean>true</boolean>
    <boolean>false</boolean>
    <boolean>false</boolean>
    <boolean>true</boolean>
    <boolean>true</boolean>
    <boolean>true</boolean>
  </ASM>
  <TSI>
    <boolean>true</boolean>
    <boolean>false</boolean>
    <boolean>false</boolean>
    <boolean>true</boolean>
    <boolean>true</boolean>
    <boolean>true</boolean>
  </TSI>
  <VMAS>
    <boolean>true</boolean>
    <boolean>true</boolean>
    <boolean>false</boolean>
    <boolean>false</boolean>
    <boolean>true</boolean>
    <boolean>true</boolean>
  </VMAS>
  <FAL>
    <boolean>false</boolean>
    <boolean>false</boolean>
    <boolean>true</boolean>
    <boolean>true</boolean>
    <boolean>true</boolean>
    <boolean>true</boolean>
  </FAL>
  <LD>
    <boolean>true</boolean>
    <boolean>false</boolean>
    <boolean>true</boolean>
    <boolean>true</boolean>
    <boolean>true</boolean>
    <boolean>true</boolean>
  </LD>
</SelfCheckSetting>